{"allergenes":[],"alternatives":[],"co2Values":[{"amount":null,"comment":"co2-calculation: Wie Karotte CH FL calculation-process-documentation: Doldenblütler","derived":false,"id":16079,"product":100,"type":"Co2Value","unit":"kg CO2 Äq/kg","validCountries":[]}],"commentsOnDensityAndUnitWeight":"","densities":[],"edb":true,"endOfLocalSeason":"None","englishName":"dill","foodWasteData":[],"frenchName":null,"id":100,"infoTextForCook":null,"name":"Dillkraut","nutrientProcesses":[],"nutrients":[{"amount":243,"comment":null,"derived":false,"id":3426,"nutrientId":7,"nutrientName":"ENERC","product":100,"reference":"EuroFIR377 Queller","referenceId":93,"type":"ProductNutrientAssociation","unit":"kJ","validCountries":[]},{"amount":243,"comment":null,"derived":false,"id":3427,"nutrientId":7,"nutrientName":"ENERC","product":100,"reference":"EuroFIR377 Queller","referenceId":93,"type":"ProductNutrientAssociation","unit":"kJ","validCountries":[]},{"amount":243,"comment":null,"derived":false,"id":3428,"nutrientId":7,"nutrientName":"ENERC","product":100,"reference":"EuroFIR377 Queller","referenceId":93,"type":"ProductNutrientAssociation","unit":"kJ","validCountries":[]},{"amount":243,"comment":null,"derived":false,"id":3429,"nutrientId":7,"nutrientName":"ENERC","product":100,"reference":"EuroFIR377 Queller","referenceId":93,"type":"ProductNutrientAssociation","unit":"kJ","validCountries":[]},{"amount":243,"comment":null,"derived":false,"id":3430,"nutrientId":7,"nutrientName":"ENERC","product":100,"reference":"EuroFIR377 Queller","referenceId":93,"type":"ProductNutrientAssociation","unit":"kJ","validCountries":[]},{"amount":243,"comment":null,"derived":false,"id":3431,"nutrientId":7,"nutrientName":"ENERC","product":100,"reference":"EuroFIR377 Queller","referenceId":93,"type":"ProductNutrientAssociation","unit":"kJ","validCountries":[]},{"amount":243,"comment":null,"derived":false,"id":3432,"nutrientId":7,"nutrientName":"ENERC","product":100,"reference":"EuroFIR377 Queller","referenceId":93,"type":"ProductNutrientAssociation","unit":"kJ","validCountries":[]}],"possibleOrigins":[],"processes":[],"processesCo2":[],"specification":null,"startOfLocalSeason":"None","synonyms":[],"tags":[],"texture":null,"unitWeights":[]}