{"allergenes":[],"alternatives":[],"co2Values":[{"amount":0.41,"comment":"co2-calculation: Average of Banane Colombia, Costa Rica, Ecuador and Peru (0.36+0.38+0.48+0.41)/4 = 0.41 calculation-process-documentation: -","derived":false,"id":865,"product":29,"type":"Co2Value","unit":"kg CO2 Äq/kg","validCountries":[]}],"commentsOnDensityAndUnitWeight":"","densities":[],"edb":true,"endOfLocalSeason":"None","englishName":"banana","foodWasteData":[],"frenchName":null,"id":29,"infoTextForCook":null,"name":"Bananen","nutrientProcesses":[],"nutrients":[{"amount":0,"comment":null,"derived":false,"id":832,"nutrientId":1,"nutrientName":"ALC","product":29,"reference":"EuroFIR1000844 Banana, raw","referenceId":29,"type":"ProductNutrientAssociation","unit":"g","validCountries":[]},{"amount":8,"comment":null,"derived":false,"id":833,"nutrientId":2,"nutrientName":"CA","product":29,"reference":"EuroFIR1000844 Banana, raw","referenceId":29,"type":"ProductNutrientAssociation","unit":"mg","validCountries":[]},{"amount":21,"comment":null,"derived":false,"id":834,"nutrientId":3,"nutrientName":"CHO","product":29,"reference":"EuroFIR1000844 Banana, raw","referenceId":29,"type":"ProductNutrientAssociation","unit":"g","validCountries":[]},{"amount":0,"comment":null,"derived":false,"id":835,"nutrientId":4,"nutrientName":"CHORL","product":29,"reference":"EuroFIR1000844 Banana, raw","referenceId":29,"type":"ProductNutrientAssociation","unit":"mg","validCountries":[]},{"amount":23,"comment":null,"derived":false,"id":836,"nutrientId":5,"nutrientName":"CHOT","product":29,"reference":"EuroFIR1000844 Banana, raw","referenceId":29,"type":"ProductNutrientAssociation","unit":"g","validCountries":[]},{"amount":109,"comment":null,"derived":false,"id":837,"nutrientId":6,"nutrientName":"CLD","product":29,"reference":"EuroFIR1000844 Banana, raw","referenceId":29,"type":"ProductNutrientAssociation","unit":"mg","validCountries":[]},{"amount":381,"comment":null,"derived":false,"id":838,"nutrientId":7,"nutrientName":"ENERC","product":29,"reference":"EuroFIR1000844 Banana, raw","referenceId":29,"type":"ProductNutrientAssociation","unit":"kJ","validCountries":[]},{"amount":0,"comment":null,"derived":false,"id":839,"nutrientId":8,"nutrientName":"FAMS","product":29,"reference":"EuroFIR1000844 Banana, raw","referenceId":29,"type":"ProductNutrientAssociation","unit":"g","validCountries":[]},{"amount":0.06,"comment":null,"derived":false,"id":840,"nutrientId":9,"nutrientName":"FAPU","product":29,"reference":"EuroFIR1000844 Banana, raw","referenceId":29,"type":"ProductNutrientAssociation","unit":"g","validCountries":[]},{"amount":0.12,"comment":null,"derived":false,"id":841,"nutrientId":10,"nutrientName":"FASAT","product":29,"reference":"EuroFIR1000844 Banana, raw","referenceId":29,"type":"ProductNutrientAssociation","unit":"g","validCountries":[]},{"amount":0.3,"comment":null,"derived":false,"id":842,"nutrientId":11,"nutrientName":"FAT","product":29,"reference":"EuroFIR1000844 Banana, raw","referenceId":29,"type":"ProductNutrientAssociation","unit":"g","validCountries":[]},{"amount":0.42,"comment":null,"derived":false,"id":843,"nutrientId":12,"nutrientName":"FE","product":29,"reference":"EuroFIR1000844 Banana, raw","referenceId":29,"type":"ProductNutrientAssociation","unit":"mg","validCountries":[]},{"amount":2,"comment":null,"derived":false,"id":844,"nutrientId":13,"nutrientName":"FIBT","product":29,"reference":"EuroFIR1000844 Banana, raw","referenceId":29,"type":"ProductNutrientAssociation","unit":"g","validCountries":[]},{"amount":23,"comment":null,"derived":false,"id":845,"nutrientId":14,"nutrientName":"FOL","product":29,"reference":"EuroFIR1000844 Banana, raw","referenceId":29,"type":"ProductNutrientAssociation","unit":"ug","validCountries":[]},{"amount":2,"comment":null,"derived":false,"id":846,"nutrientId":15,"nutrientName":"ID","product":29,"reference":"EuroFIR1000844 Banana, raw","referenceId":29,"type":"ProductNutrientAssociation","unit":"ug","validCountries":[]},{"amount":385,"comment":null,"derived":false,"id":847,"nutrientId":16,"nutrientName":"K","product":29,"reference":"EuroFIR1000844 Banana, raw","referenceId":29,"type":"ProductNutrientAssociation","unit":"mg","validCountries":[]},{"amount":30,"comment":null,"derived":false,"id":848,"nutrientId":17,"nutrientName":"MG","product":29,"reference":"EuroFIR1000844 Banana, raw","referenceId":29,"type":"ProductNutrientAssociation","unit":"mg","validCountries":[]},{"amount":1,"comment":null,"derived":false,"id":849,"nutrientId":18,"nutrientName":"NA","product":29,"reference":"EuroFIR1000844 Banana, raw","referenceId":29,"type":"ProductNutrientAssociation","unit":"mg","validCountries":[]},{"amount":0.6,"comment":null,"derived":false,"id":850,"nutrientId":19,"nutrientName":"NIA","product":29,"reference":"EuroFIR1000844 Banana, raw","referenceId":29,"type":"ProductNutrientAssociation","unit":"mg","validCountries":[]},{"amount":22,"comment":null,"derived":false,"id":851,"nutrientId":20,"nutrientName":"P","product":29,"reference":"EuroFIR1000844 Banana, raw","referenceId":29,"type":"ProductNutrientAssociation","unit":"mg","validCountries":[]},{"amount":0.3,"comment":null,"derived":false,"id":852,"nutrientId":21,"nutrientName":"PANTAC","product":29,"reference":"EuroFIR1000844 Banana, raw","referenceId":29,"type":"ProductNutrientAssociation","unit":"mg","validCountries":[]},{"amount":1.1,"comment":null,"derived":false,"id":853,"nutrientId":22,"nutrientName":"PROT","product":29,"reference":"EuroFIR1000844 Banana, raw","referenceId":29,"type":"ProductNutrientAssociation","unit":"g","validCountries":[]},{"amount":0.07,"comment":null,"derived":false,"id":854,"nutrientId":23,"nutrientName":"RIBF","product":29,"reference":"EuroFIR1000844 Banana, raw","referenceId":29,"type":"ProductNutrientAssociation","unit":"mg","validCountries":[]},{"amount":3.8,"comment":null,"derived":false,"id":855,"nutrientId":24,"nutrientName":"STARCH","product":29,"reference":"EuroFIR1000844 Banana, raw","referenceId":29,"type":"ProductNutrientAssociation","unit":"g","validCountries":[]},{"amount":17.2,"comment":null,"derived":false,"id":856,"nutrientId":25,"nutrientName":"SUGAR","product":29,"reference":"EuroFIR1000844 Banana, raw","referenceId":29,"type":"ProductNutrientAssociation","unit":"g","validCountries":[]},{"amount":0.04,"comment":null,"derived":false,"id":857,"nutrientId":26,"nutrientName":"THIA","product":29,"reference":"EuroFIR1000844 Banana, raw","referenceId":29,"type":"ProductNutrientAssociation","unit":"mg","validCountries":[]},{"amount":0,"comment":null,"derived":false,"id":858,"nutrientId":27,"nutrientName":"VITB12","product":29,"reference":"EuroFIR1000844 Banana, raw","referenceId":29,"type":"ProductNutrientAssociation","unit":"ug","validCountries":[]},{"amount":0.47,"comment":null,"derived":false,"id":859,"nutrientId":28,"nutrientName":"VITB6","product":29,"reference":"EuroFIR1000844 Banana, raw","referenceId":29,"type":"ProductNutrientAssociation","unit":"mg","validCountries":[]},{"amount":12,"comment":null,"derived":false,"id":860,"nutrientId":29,"nutrientName":"VITC","product":29,"reference":"EuroFIR1000844 Banana, raw","referenceId":29,"type":"ProductNutrientAssociation","unit":"mg","validCountries":[]},{"amount":0,"comment":null,"derived":false,"id":861,"nutrientId":30,"nutrientName":"VITD","product":29,"reference":"EuroFIR1000844 Banana, raw","referenceId":29,"type":"ProductNutrientAssociation","unit":"ug","validCountries":[]},{"amount":0.29,"comment":null,"derived":false,"id":862,"nutrientId":31,"nutrientName":"VITE","product":29,"reference":"EuroFIR1000844 Banana, raw","referenceId":29,"type":"ProductNutrientAssociation","unit":"ATE","validCountries":[]},{"amount":74,"comment":null,"derived":false,"id":863,"nutrientId":32,"nutrientName":"WATER","product":29,"reference":"EuroFIR1000844 Banana, raw","referenceId":29,"type":"ProductNutrientAssociation","unit":"g","validCountries":[]},{"amount":0.193,"comment":null,"derived":false,"id":864,"nutrientId":33,"nutrientName":"ZN","product":29,"reference":"EuroFIR1000844 Banana, raw","referenceId":29,"type":"ProductNutrientAssociation","unit":"mg","validCountries":[]}],"possibleOrigins":[],"processes":[],"processesCo2":[],"specification":null,"startOfLocalSeason":"None","synonyms":[],"tags":[],"texture":null,"unitWeights":[]}