{"allergenes":[],"alternatives":[],"co2Values":[{"amount":0.2,"comment":"co2-calculation: value estimated from figure in reference (1).  calculation-process-documentation: -","derived":false,"id":6416,"product":193,"type":"Co2Value","unit":"kg CO2 Äq/kg","validCountries":[]}],"commentsOnDensityAndUnitWeight":"","densities":[],"edb":true,"endOfLocalSeason":"None","englishName":"mushrooms","foodWasteData":[],"frenchName":null,"id":193,"infoTextForCook":null,"name":"Champignons","nutrientProcesses":[],"nutrients":[{"amount":0.2,"comment":null,"derived":false,"id":6383,"nutrientId":1,"nutrientName":"ALC","product":193,"reference":"EuroFIR1000838 Mushroom, raw","referenceId":166,"type":"ProductNutrientAssociation","unit":"g","validCountries":[]},{"amount":0.2,"comment":null,"derived":false,"id":6384,"nutrientId":2,"nutrientName":"CA","product":193,"reference":"EuroFIR1000838 Mushroom, raw","referenceId":166,"type":"ProductNutrientAssociation","unit":"mg","validCountries":[]},{"amount":0.2,"comment":null,"derived":false,"id":6385,"nutrientId":3,"nutrientName":"CHO","product":193,"reference":"EuroFIR1000838 Mushroom, raw","referenceId":166,"type":"ProductNutrientAssociation","unit":"g","validCountries":[]},{"amount":0.2,"comment":null,"derived":false,"id":6386,"nutrientId":4,"nutrientName":"CHORL","product":193,"reference":"EuroFIR1000838 Mushroom, raw","referenceId":166,"type":"ProductNutrientAssociation","unit":"mg","validCountries":[]},{"amount":0.2,"comment":null,"derived":false,"id":6387,"nutrientId":5,"nutrientName":"CHOT","product":193,"reference":"EuroFIR1000838 Mushroom, raw","referenceId":166,"type":"ProductNutrientAssociation","unit":"g","validCountries":[]},{"amount":0.2,"comment":null,"derived":false,"id":6388,"nutrientId":6,"nutrientName":"CLD","product":193,"reference":"EuroFIR1000838 Mushroom, raw","referenceId":166,"type":"ProductNutrientAssociation","unit":"mg","validCountries":[]},{"amount":0.2,"comment":null,"derived":false,"id":6389,"nutrientId":7,"nutrientName":"ENERC","product":193,"reference":"EuroFIR1000838 Mushroom, raw","referenceId":166,"type":"ProductNutrientAssociation","unit":"kJ","validCountries":[]},{"amount":0.2,"comment":null,"derived":false,"id":6390,"nutrientId":8,"nutrientName":"FAMS","product":193,"reference":"EuroFIR1000838 Mushroom, raw","referenceId":166,"type":"ProductNutrientAssociation","unit":"g","validCountries":[]},{"amount":0.2,"comment":null,"derived":false,"id":6391,"nutrientId":9,"nutrientName":"FAPU","product":193,"reference":"EuroFIR1000838 Mushroom, raw","referenceId":166,"type":"ProductNutrientAssociation","unit":"g","validCountries":[]},{"amount":0.2,"comment":null,"derived":false,"id":6392,"nutrientId":10,"nutrientName":"FASAT","product":193,"reference":"EuroFIR1000838 Mushroom, raw","referenceId":166,"type":"ProductNutrientAssociation","unit":"g","validCountries":[]},{"amount":0.2,"comment":null,"derived":false,"id":6393,"nutrientId":11,"nutrientName":"FAT","product":193,"reference":"EuroFIR1000838 Mushroom, raw","referenceId":166,"type":"ProductNutrientAssociation","unit":"g","validCountries":[]},{"amount":0.2,"comment":null,"derived":false,"id":6394,"nutrientId":12,"nutrientName":"FE","product":193,"reference":"EuroFIR1000838 Mushroom, raw","referenceId":166,"type":"ProductNutrientAssociation","unit":"mg","validCountries":[]},{"amount":0.2,"comment":null,"derived":false,"id":6395,"nutrientId":13,"nutrientName":"FIBT","product":193,"reference":"EuroFIR1000838 Mushroom, raw","referenceId":166,"type":"ProductNutrientAssociation","unit":"g","validCountries":[]},{"amount":0.2,"comment":null,"derived":false,"id":6396,"nutrientId":14,"nutrientName":"FOL","product":193,"reference":"EuroFIR1000838 Mushroom, raw","referenceId":166,"type":"ProductNutrientAssociation","unit":"ug","validCountries":[]},{"amount":0.2,"comment":null,"derived":false,"id":6397,"nutrientId":15,"nutrientName":"ID","product":193,"reference":"EuroFIR1000838 Mushroom, raw","referenceId":166,"type":"ProductNutrientAssociation","unit":"ug","validCountries":[]},{"amount":0.2,"comment":null,"derived":false,"id":6398,"nutrientId":16,"nutrientName":"K","product":193,"reference":"EuroFIR1000838 Mushroom, raw","referenceId":166,"type":"ProductNutrientAssociation","unit":"mg","validCountries":[]},{"amount":0.2,"comment":null,"derived":false,"id":6399,"nutrientId":17,"nutrientName":"MG","product":193,"reference":"EuroFIR1000838 Mushroom, raw","referenceId":166,"type":"ProductNutrientAssociation","unit":"mg","validCountries":[]},{"amount":0.2,"comment":null,"derived":false,"id":6400,"nutrientId":18,"nutrientName":"NA","product":193,"reference":"EuroFIR1000838 Mushroom, raw","referenceId":166,"type":"ProductNutrientAssociation","unit":"mg","validCountries":[]},{"amount":0.2,"comment":null,"derived":false,"id":6401,"nutrientId":19,"nutrientName":"NIA","product":193,"reference":"EuroFIR1000838 Mushroom, raw","referenceId":166,"type":"ProductNutrientAssociation","unit":"mg","validCountries":[]},{"amount":0.2,"comment":null,"derived":false,"id":6402,"nutrientId":20,"nutrientName":"P","product":193,"reference":"EuroFIR1000838 Mushroom, raw","referenceId":166,"type":"ProductNutrientAssociation","unit":"mg","validCountries":[]},{"amount":0.2,"comment":null,"derived":false,"id":6403,"nutrientId":21,"nutrientName":"PANTAC","product":193,"reference":"EuroFIR1000838 Mushroom, raw","referenceId":166,"type":"ProductNutrientAssociation","unit":"mg","validCountries":[]},{"amount":0.2,"comment":null,"derived":false,"id":6404,"nutrientId":22,"nutrientName":"PROT","product":193,"reference":"EuroFIR1000838 Mushroom, raw","referenceId":166,"type":"ProductNutrientAssociation","unit":"g","validCountries":[]},{"amount":0.2,"comment":null,"derived":false,"id":6405,"nutrientId":23,"nutrientName":"RIBF","product":193,"reference":"EuroFIR1000838 Mushroom, raw","referenceId":166,"type":"ProductNutrientAssociation","unit":"mg","validCountries":[]},{"amount":0.2,"comment":null,"derived":false,"id":6406,"nutrientId":24,"nutrientName":"STARCH","product":193,"reference":"EuroFIR1000838 Mushroom, raw","referenceId":166,"type":"ProductNutrientAssociation","unit":"g","validCountries":[]},{"amount":0.2,"comment":null,"derived":false,"id":6407,"nutrientId":25,"nutrientName":"SUGAR","product":193,"reference":"EuroFIR1000838 Mushroom, raw","referenceId":166,"type":"ProductNutrientAssociation","unit":"g","validCountries":[]},{"amount":0.2,"comment":null,"derived":false,"id":6408,"nutrientId":26,"nutrientName":"THIA","product":193,"reference":"EuroFIR1000838 Mushroom, raw","referenceId":166,"type":"ProductNutrientAssociation","unit":"mg","validCountries":[]},{"amount":0.2,"comment":null,"derived":false,"id":6409,"nutrientId":27,"nutrientName":"VITB12","product":193,"reference":"EuroFIR1000838 Mushroom, raw","referenceId":166,"type":"ProductNutrientAssociation","unit":"ug","validCountries":[]},{"amount":0.2,"comment":null,"derived":false,"id":6410,"nutrientId":28,"nutrientName":"VITB6","product":193,"reference":"EuroFIR1000838 Mushroom, raw","referenceId":166,"type":"ProductNutrientAssociation","unit":"mg","validCountries":[]},{"amount":0.2,"comment":null,"derived":false,"id":6411,"nutrientId":29,"nutrientName":"VITC","product":193,"reference":"EuroFIR1000838 Mushroom, raw","referenceId":166,"type":"ProductNutrientAssociation","unit":"mg","validCountries":[]},{"amount":0.2,"comment":null,"derived":false,"id":6412,"nutrientId":30,"nutrientName":"VITD","product":193,"reference":"EuroFIR1000838 Mushroom, raw","referenceId":166,"type":"ProductNutrientAssociation","unit":"ug","validCountries":[]},{"amount":0.2,"comment":null,"derived":false,"id":6413,"nutrientId":31,"nutrientName":"VITE","product":193,"reference":"EuroFIR1000838 Mushroom, raw","referenceId":166,"type":"ProductNutrientAssociation","unit":"ATE","validCountries":[]},{"amount":0.2,"comment":null,"derived":false,"id":6414,"nutrientId":32,"nutrientName":"WATER","product":193,"reference":"EuroFIR1000838 Mushroom, raw","referenceId":166,"type":"ProductNutrientAssociation","unit":"g","validCountries":[]},{"amount":0.2,"comment":null,"derived":false,"id":6415,"nutrientId":33,"nutrientName":"ZN","product":193,"reference":"EuroFIR1000838 Mushroom, raw","referenceId":166,"type":"ProductNutrientAssociation","unit":"mg","validCountries":[]}],"possibleOrigins":[],"processes":[],"processesCo2":[],"specification":null,"startOfLocalSeason":"None","synonyms":[],"tags":[],"texture":null,"unitWeights":[]}