{"allergenes":[],"alternatives":[],"co2Values":[{"amount":0.2,"comment":"co2-calculation: Wert von Knollensellerie FL CH calculation-process-documentation: -","derived":false,"id":412,"product":15,"type":"Co2Value","unit":"kg CO2 Äq/kg","validCountries":[]}],"commentsOnDensityAndUnitWeight":"","densities":[],"edb":true,"endOfLocalSeason":"None","englishName":"celery root","foodWasteData":[],"frenchName":null,"id":15,"infoTextForCook":null,"name":"Knollensellerie","nutrientProcesses":[],"nutrients":[{"amount":0.2,"comment":null,"derived":false,"id":379,"nutrientId":1,"nutrientName":"ALC","product":15,"reference":"EuroFIR1000820 Celeriac, raw","referenceId":15,"type":"ProductNutrientAssociation","unit":"g","validCountries":[]},{"amount":0.2,"comment":null,"derived":false,"id":380,"nutrientId":2,"nutrientName":"CA","product":15,"reference":"EuroFIR1000820 Celeriac, raw","referenceId":15,"type":"ProductNutrientAssociation","unit":"mg","validCountries":[]},{"amount":0.2,"comment":null,"derived":false,"id":381,"nutrientId":3,"nutrientName":"CHO","product":15,"reference":"EuroFIR1000820 Celeriac, raw","referenceId":15,"type":"ProductNutrientAssociation","unit":"g","validCountries":[]},{"amount":0.2,"comment":null,"derived":false,"id":382,"nutrientId":4,"nutrientName":"CHORL","product":15,"reference":"EuroFIR1000820 Celeriac, raw","referenceId":15,"type":"ProductNutrientAssociation","unit":"mg","validCountries":[]},{"amount":0.2,"comment":null,"derived":false,"id":383,"nutrientId":5,"nutrientName":"CHOT","product":15,"reference":"EuroFIR1000820 Celeriac, raw","referenceId":15,"type":"ProductNutrientAssociation","unit":"g","validCountries":[]},{"amount":0.2,"comment":null,"derived":false,"id":384,"nutrientId":6,"nutrientName":"CLD","product":15,"reference":"EuroFIR1000820 Celeriac, raw","referenceId":15,"type":"ProductNutrientAssociation","unit":"mg","validCountries":[]},{"amount":0.2,"comment":null,"derived":false,"id":385,"nutrientId":7,"nutrientName":"ENERC","product":15,"reference":"EuroFIR1000820 Celeriac, raw","referenceId":15,"type":"ProductNutrientAssociation","unit":"kJ","validCountries":[]},{"amount":0.2,"comment":null,"derived":false,"id":386,"nutrientId":8,"nutrientName":"FAMS","product":15,"reference":"EuroFIR1000820 Celeriac, raw","referenceId":15,"type":"ProductNutrientAssociation","unit":"g","validCountries":[]},{"amount":0.2,"comment":null,"derived":false,"id":387,"nutrientId":9,"nutrientName":"FAPU","product":15,"reference":"EuroFIR1000820 Celeriac, raw","referenceId":15,"type":"ProductNutrientAssociation","unit":"g","validCountries":[]},{"amount":0.2,"comment":null,"derived":false,"id":388,"nutrientId":10,"nutrientName":"FASAT","product":15,"reference":"EuroFIR1000820 Celeriac, raw","referenceId":15,"type":"ProductNutrientAssociation","unit":"g","validCountries":[]},{"amount":0.2,"comment":null,"derived":false,"id":389,"nutrientId":11,"nutrientName":"FAT","product":15,"reference":"EuroFIR1000820 Celeriac, raw","referenceId":15,"type":"ProductNutrientAssociation","unit":"g","validCountries":[]},{"amount":0.2,"comment":null,"derived":false,"id":390,"nutrientId":12,"nutrientName":"FE","product":15,"reference":"EuroFIR1000820 Celeriac, raw","referenceId":15,"type":"ProductNutrientAssociation","unit":"mg","validCountries":[]},{"amount":0.2,"comment":null,"derived":false,"id":391,"nutrientId":13,"nutrientName":"FIBT","product":15,"reference":"EuroFIR1000820 Celeriac, raw","referenceId":15,"type":"ProductNutrientAssociation","unit":"g","validCountries":[]},{"amount":0.2,"comment":null,"derived":false,"id":392,"nutrientId":14,"nutrientName":"FOL","product":15,"reference":"EuroFIR1000820 Celeriac, raw","referenceId":15,"type":"ProductNutrientAssociation","unit":"ug","validCountries":[]},{"amount":0.2,"comment":null,"derived":false,"id":393,"nutrientId":15,"nutrientName":"ID","product":15,"reference":"EuroFIR1000820 Celeriac, raw","referenceId":15,"type":"ProductNutrientAssociation","unit":"ug","validCountries":[]},{"amount":0.2,"comment":null,"derived":false,"id":394,"nutrientId":16,"nutrientName":"K","product":15,"reference":"EuroFIR1000820 Celeriac, raw","referenceId":15,"type":"ProductNutrientAssociation","unit":"mg","validCountries":[]},{"amount":0.2,"comment":null,"derived":false,"id":395,"nutrientId":17,"nutrientName":"MG","product":15,"reference":"EuroFIR1000820 Celeriac, raw","referenceId":15,"type":"ProductNutrientAssociation","unit":"mg","validCountries":[]},{"amount":0.2,"comment":null,"derived":false,"id":396,"nutrientId":18,"nutrientName":"NA","product":15,"reference":"EuroFIR1000820 Celeriac, raw","referenceId":15,"type":"ProductNutrientAssociation","unit":"mg","validCountries":[]},{"amount":0.2,"comment":null,"derived":false,"id":397,"nutrientId":19,"nutrientName":"NIA","product":15,"reference":"EuroFIR1000820 Celeriac, raw","referenceId":15,"type":"ProductNutrientAssociation","unit":"mg","validCountries":[]},{"amount":0.2,"comment":null,"derived":false,"id":398,"nutrientId":20,"nutrientName":"P","product":15,"reference":"EuroFIR1000820 Celeriac, raw","referenceId":15,"type":"ProductNutrientAssociation","unit":"mg","validCountries":[]},{"amount":0.2,"comment":null,"derived":false,"id":399,"nutrientId":21,"nutrientName":"PANTAC","product":15,"reference":"EuroFIR1000820 Celeriac, raw","referenceId":15,"type":"ProductNutrientAssociation","unit":"mg","validCountries":[]},{"amount":0.2,"comment":null,"derived":false,"id":400,"nutrientId":22,"nutrientName":"PROT","product":15,"reference":"EuroFIR1000820 Celeriac, raw","referenceId":15,"type":"ProductNutrientAssociation","unit":"g","validCountries":[]},{"amount":0.2,"comment":null,"derived":false,"id":401,"nutrientId":23,"nutrientName":"RIBF","product":15,"reference":"EuroFIR1000820 Celeriac, raw","referenceId":15,"type":"ProductNutrientAssociation","unit":"mg","validCountries":[]},{"amount":0.2,"comment":null,"derived":false,"id":402,"nutrientId":24,"nutrientName":"STARCH","product":15,"reference":"EuroFIR1000820 Celeriac, raw","referenceId":15,"type":"ProductNutrientAssociation","unit":"g","validCountries":[]},{"amount":0.2,"comment":null,"derived":false,"id":403,"nutrientId":25,"nutrientName":"SUGAR","product":15,"reference":"EuroFIR1000820 Celeriac, raw","referenceId":15,"type":"ProductNutrientAssociation","unit":"g","validCountries":[]},{"amount":0.2,"comment":null,"derived":false,"id":404,"nutrientId":26,"nutrientName":"THIA","product":15,"reference":"EuroFIR1000820 Celeriac, raw","referenceId":15,"type":"ProductNutrientAssociation","unit":"mg","validCountries":[]},{"amount":0.2,"comment":null,"derived":false,"id":405,"nutrientId":27,"nutrientName":"VITB12","product":15,"reference":"EuroFIR1000820 Celeriac, raw","referenceId":15,"type":"ProductNutrientAssociation","unit":"ug","validCountries":[]},{"amount":0.2,"comment":null,"derived":false,"id":406,"nutrientId":28,"nutrientName":"VITB6","product":15,"reference":"EuroFIR1000820 Celeriac, raw","referenceId":15,"type":"ProductNutrientAssociation","unit":"mg","validCountries":[]},{"amount":0.2,"comment":null,"derived":false,"id":407,"nutrientId":29,"nutrientName":"VITC","product":15,"reference":"EuroFIR1000820 Celeriac, raw","referenceId":15,"type":"ProductNutrientAssociation","unit":"mg","validCountries":[]},{"amount":0.2,"comment":null,"derived":false,"id":408,"nutrientId":30,"nutrientName":"VITD","product":15,"reference":"EuroFIR1000820 Celeriac, raw","referenceId":15,"type":"ProductNutrientAssociation","unit":"ug","validCountries":[]},{"amount":0.2,"comment":null,"derived":false,"id":409,"nutrientId":31,"nutrientName":"VITE","product":15,"reference":"EuroFIR1000820 Celeriac, raw","referenceId":15,"type":"ProductNutrientAssociation","unit":"ATE","validCountries":[]},{"amount":0.2,"comment":null,"derived":false,"id":410,"nutrientId":32,"nutrientName":"WATER","product":15,"reference":"EuroFIR1000820 Celeriac, raw","referenceId":15,"type":"ProductNutrientAssociation","unit":"g","validCountries":[]},{"amount":0.2,"comment":null,"derived":false,"id":411,"nutrientId":33,"nutrientName":"ZN","product":15,"reference":"EuroFIR1000820 Celeriac, raw","referenceId":15,"type":"ProductNutrientAssociation","unit":"mg","validCountries":[]}],"possibleOrigins":[],"processes":[],"processesCo2":[],"specification":null,"startOfLocalSeason":"None","synonyms":[],"tags":[],"texture":null,"unitWeights":[]}