{"allergenes":[],"alternatives":[],"co2Values":[{"amount":0.573,"comment":"co2-calculation: - calculation-process-documentation: -","derived":false,"id":12243,"product":366,"type":"Co2Value","unit":"kg CO2 Äq/kg","validCountries":[]}],"commentsOnDensityAndUnitWeight":"","densities":[],"edb":true,"endOfLocalSeason":"None","englishName":"lemonade (whey based)","foodWasteData":[],"frenchName":null,"id":366,"infoTextForCook":null,"name":"Limonade","nutrientProcesses":[],"nutrients":[{"amount":0,"comment":null,"derived":false,"id":12221,"nutrientId":1,"nutrientName":"ALC","product":366,"reference":"EuroFIR851002 Rivella blue","referenceId":319,"type":"ProductNutrientAssociation","unit":"g","validCountries":[]},{"amount":16.5,"comment":null,"derived":false,"id":12222,"nutrientId":2,"nutrientName":"CA","product":366,"reference":"EuroFIR851002 Rivella blue","referenceId":319,"type":"ProductNutrientAssociation","unit":"mg","validCountries":[]},{"amount":1.4,"comment":null,"derived":false,"id":12223,"nutrientId":3,"nutrientName":"CHO","product":366,"reference":"EuroFIR851002 Rivella blue","referenceId":319,"type":"ProductNutrientAssociation","unit":"g","validCountries":[]},{"amount":1.4,"comment":null,"derived":false,"id":12224,"nutrientId":5,"nutrientName":"CHOT","product":366,"reference":"EuroFIR851002 Rivella blue","referenceId":319,"type":"ProductNutrientAssociation","unit":"g","validCountries":[]},{"amount":33,"comment":null,"derived":false,"id":12225,"nutrientId":6,"nutrientName":"CLD","product":366,"reference":"EuroFIR851002 Rivella blue","referenceId":319,"type":"ProductNutrientAssociation","unit":"mg","validCountries":[]},{"amount":30,"comment":null,"derived":false,"id":12226,"nutrientId":7,"nutrientName":"ENERC","product":366,"reference":"EuroFIR851002 Rivella blue","referenceId":319,"type":"ProductNutrientAssociation","unit":"kJ","validCountries":[]},{"amount":0,"comment":null,"derived":false,"id":12227,"nutrientId":8,"nutrientName":"FAMS","product":366,"reference":"EuroFIR851002 Rivella blue","referenceId":319,"type":"ProductNutrientAssociation","unit":"g","validCountries":[]},{"amount":0,"comment":null,"derived":false,"id":12228,"nutrientId":9,"nutrientName":"FAPU","product":366,"reference":"EuroFIR851002 Rivella blue","referenceId":319,"type":"ProductNutrientAssociation","unit":"g","validCountries":[]},{"amount":0,"comment":null,"derived":false,"id":12229,"nutrientId":10,"nutrientName":"FASAT","product":366,"reference":"EuroFIR851002 Rivella blue","referenceId":319,"type":"ProductNutrientAssociation","unit":"g","validCountries":[]},{"amount":0,"comment":null,"derived":false,"id":12230,"nutrientId":11,"nutrientName":"FAT","product":366,"reference":"EuroFIR851002 Rivella blue","referenceId":319,"type":"ProductNutrientAssociation","unit":"g","validCountries":[]},{"amount":0,"comment":null,"derived":false,"id":12231,"nutrientId":13,"nutrientName":"FIBT","product":366,"reference":"EuroFIR851002 Rivella blue","referenceId":319,"type":"ProductNutrientAssociation","unit":"g","validCountries":[]},{"amount":45,"comment":null,"derived":false,"id":12232,"nutrientId":16,"nutrientName":"K","product":366,"reference":"EuroFIR851002 Rivella blue","referenceId":319,"type":"ProductNutrientAssociation","unit":"mg","validCountries":[]},{"amount":3.5,"comment":null,"derived":false,"id":12233,"nutrientId":17,"nutrientName":"MG","product":366,"reference":"EuroFIR851002 Rivella blue","referenceId":319,"type":"ProductNutrientAssociation","unit":"mg","validCountries":[]},{"amount":13,"comment":null,"derived":false,"id":12234,"nutrientId":18,"nutrientName":"NA","product":366,"reference":"EuroFIR851002 Rivella blue","referenceId":319,"type":"ProductNutrientAssociation","unit":"mg","validCountries":[]},{"amount":10,"comment":null,"derived":false,"id":12235,"nutrientId":20,"nutrientName":"P","product":366,"reference":"EuroFIR851002 Rivella blue","referenceId":319,"type":"ProductNutrientAssociation","unit":"mg","validCountries":[]},{"amount":0,"comment":null,"derived":false,"id":12236,"nutrientId":22,"nutrientName":"PROT","product":366,"reference":"EuroFIR851002 Rivella blue","referenceId":319,"type":"ProductNutrientAssociation","unit":"g","validCountries":[]},{"amount":0,"comment":null,"derived":false,"id":12237,"nutrientId":23,"nutrientName":"RIBF","product":366,"reference":"EuroFIR851002 Rivella blue","referenceId":319,"type":"ProductNutrientAssociation","unit":"mg","validCountries":[]},{"amount":1.4,"comment":null,"derived":false,"id":12238,"nutrientId":25,"nutrientName":"SUGAR","product":366,"reference":"EuroFIR851002 Rivella blue","referenceId":319,"type":"ProductNutrientAssociation","unit":"g","validCountries":[]},{"amount":0,"comment":null,"derived":false,"id":12239,"nutrientId":26,"nutrientName":"THIA","product":366,"reference":"EuroFIR851002 Rivella blue","referenceId":319,"type":"ProductNutrientAssociation","unit":"mg","validCountries":[]},{"amount":0,"comment":null,"derived":false,"id":12240,"nutrientId":27,"nutrientName":"VITB12","product":366,"reference":"EuroFIR851002 Rivella blue","referenceId":319,"type":"ProductNutrientAssociation","unit":"ug","validCountries":[]},{"amount":0,"comment":null,"derived":false,"id":12241,"nutrientId":28,"nutrientName":"VITB6","product":366,"reference":"EuroFIR851002 Rivella blue","referenceId":319,"type":"ProductNutrientAssociation","unit":"mg","validCountries":[]},{"amount":98.8,"comment":null,"derived":false,"id":12242,"nutrientId":32,"nutrientName":"WATER","product":366,"reference":"EuroFIR851002 Rivella blue","referenceId":319,"type":"ProductNutrientAssociation","unit":"g","validCountries":[]}],"possibleOrigins":[],"processes":[],"processesCo2":[],"specification":"Molkenbasis","startOfLocalSeason":"None","synonyms":[],"tags":[],"texture":null,"unitWeights":[]}