{"allergenes":[],"alternatives":[],"co2Values":[{"amount":0.2,"comment":"co2-calculation: - calculation-process-documentation: -","derived":false,"id":9414,"product":289,"type":"Co2Value","unit":"kg CO2 Äq/kg","validCountries":[]}],"commentsOnDensityAndUnitWeight":"","densities":[],"edb":true,"endOfLocalSeason":"None","englishName":"cheese (soft)","foodWasteData":[],"frenchName":null,"id":289,"infoTextForCook":null,"name":"Käse","nutrientProcesses":[],"nutrients":[{"amount":0.2,"comment":null,"derived":false,"id":9381,"nutrientId":1,"nutrientName":"ALC","product":289,"reference":"EuroFIR1001182 Soft cheese, 60% fidm","referenceId":255,"type":"ProductNutrientAssociation","unit":"g","validCountries":[]},{"amount":0.2,"comment":null,"derived":false,"id":9382,"nutrientId":2,"nutrientName":"CA","product":289,"reference":"EuroFIR1001182 Soft cheese, 60% fidm","referenceId":255,"type":"ProductNutrientAssociation","unit":"mg","validCountries":[]},{"amount":0.2,"comment":null,"derived":false,"id":9383,"nutrientId":3,"nutrientName":"CHO","product":289,"reference":"EuroFIR1001182 Soft cheese, 60% fidm","referenceId":255,"type":"ProductNutrientAssociation","unit":"g","validCountries":[]},{"amount":0.2,"comment":null,"derived":false,"id":9384,"nutrientId":4,"nutrientName":"CHORL","product":289,"reference":"EuroFIR1001182 Soft cheese, 60% fidm","referenceId":255,"type":"ProductNutrientAssociation","unit":"mg","validCountries":[]},{"amount":0.2,"comment":null,"derived":false,"id":9385,"nutrientId":5,"nutrientName":"CHOT","product":289,"reference":"EuroFIR1001182 Soft cheese, 60% fidm","referenceId":255,"type":"ProductNutrientAssociation","unit":"g","validCountries":[]},{"amount":0.2,"comment":null,"derived":false,"id":9386,"nutrientId":6,"nutrientName":"CLD","product":289,"reference":"EuroFIR1001182 Soft cheese, 60% fidm","referenceId":255,"type":"ProductNutrientAssociation","unit":"mg","validCountries":[]},{"amount":0.2,"comment":null,"derived":false,"id":9387,"nutrientId":7,"nutrientName":"ENERC","product":289,"reference":"EuroFIR1001182 Soft cheese, 60% fidm","referenceId":255,"type":"ProductNutrientAssociation","unit":"kJ","validCountries":[]},{"amount":0.2,"comment":null,"derived":false,"id":9388,"nutrientId":8,"nutrientName":"FAMS","product":289,"reference":"EuroFIR1001182 Soft cheese, 60% fidm","referenceId":255,"type":"ProductNutrientAssociation","unit":"g","validCountries":[]},{"amount":0.2,"comment":null,"derived":false,"id":9389,"nutrientId":9,"nutrientName":"FAPU","product":289,"reference":"EuroFIR1001182 Soft cheese, 60% fidm","referenceId":255,"type":"ProductNutrientAssociation","unit":"g","validCountries":[]},{"amount":0.2,"comment":null,"derived":false,"id":9390,"nutrientId":10,"nutrientName":"FASAT","product":289,"reference":"EuroFIR1001182 Soft cheese, 60% fidm","referenceId":255,"type":"ProductNutrientAssociation","unit":"g","validCountries":[]},{"amount":0.2,"comment":null,"derived":false,"id":9391,"nutrientId":11,"nutrientName":"FAT","product":289,"reference":"EuroFIR1001182 Soft cheese, 60% fidm","referenceId":255,"type":"ProductNutrientAssociation","unit":"g","validCountries":[]},{"amount":0.2,"comment":null,"derived":false,"id":9392,"nutrientId":12,"nutrientName":"FE","product":289,"reference":"EuroFIR1001182 Soft cheese, 60% fidm","referenceId":255,"type":"ProductNutrientAssociation","unit":"mg","validCountries":[]},{"amount":0.2,"comment":null,"derived":false,"id":9393,"nutrientId":13,"nutrientName":"FIBT","product":289,"reference":"EuroFIR1001182 Soft cheese, 60% fidm","referenceId":255,"type":"ProductNutrientAssociation","unit":"g","validCountries":[]},{"amount":0.2,"comment":null,"derived":false,"id":9394,"nutrientId":14,"nutrientName":"FOL","product":289,"reference":"EuroFIR1001182 Soft cheese, 60% fidm","referenceId":255,"type":"ProductNutrientAssociation","unit":"ug","validCountries":[]},{"amount":0.2,"comment":null,"derived":false,"id":9395,"nutrientId":15,"nutrientName":"ID","product":289,"reference":"EuroFIR1001182 Soft cheese, 60% fidm","referenceId":255,"type":"ProductNutrientAssociation","unit":"ug","validCountries":[]},{"amount":0.2,"comment":null,"derived":false,"id":9396,"nutrientId":16,"nutrientName":"K","product":289,"reference":"EuroFIR1001182 Soft cheese, 60% fidm","referenceId":255,"type":"ProductNutrientAssociation","unit":"mg","validCountries":[]},{"amount":0.2,"comment":null,"derived":false,"id":9397,"nutrientId":17,"nutrientName":"MG","product":289,"reference":"EuroFIR1001182 Soft cheese, 60% fidm","referenceId":255,"type":"ProductNutrientAssociation","unit":"mg","validCountries":[]},{"amount":0.2,"comment":null,"derived":false,"id":9398,"nutrientId":18,"nutrientName":"NA","product":289,"reference":"EuroFIR1001182 Soft cheese, 60% fidm","referenceId":255,"type":"ProductNutrientAssociation","unit":"mg","validCountries":[]},{"amount":0.2,"comment":null,"derived":false,"id":9399,"nutrientId":19,"nutrientName":"NIA","product":289,"reference":"EuroFIR1001182 Soft cheese, 60% fidm","referenceId":255,"type":"ProductNutrientAssociation","unit":"mg","validCountries":[]},{"amount":0.2,"comment":null,"derived":false,"id":9400,"nutrientId":20,"nutrientName":"P","product":289,"reference":"EuroFIR1001182 Soft cheese, 60% fidm","referenceId":255,"type":"ProductNutrientAssociation","unit":"mg","validCountries":[]},{"amount":0.2,"comment":null,"derived":false,"id":9401,"nutrientId":21,"nutrientName":"PANTAC","product":289,"reference":"EuroFIR1001182 Soft cheese, 60% fidm","referenceId":255,"type":"ProductNutrientAssociation","unit":"mg","validCountries":[]},{"amount":0.2,"comment":null,"derived":false,"id":9402,"nutrientId":22,"nutrientName":"PROT","product":289,"reference":"EuroFIR1001182 Soft cheese, 60% fidm","referenceId":255,"type":"ProductNutrientAssociation","unit":"g","validCountries":[]},{"amount":0.2,"comment":null,"derived":false,"id":9403,"nutrientId":23,"nutrientName":"RIBF","product":289,"reference":"EuroFIR1001182 Soft cheese, 60% fidm","referenceId":255,"type":"ProductNutrientAssociation","unit":"mg","validCountries":[]},{"amount":0.2,"comment":null,"derived":false,"id":9404,"nutrientId":24,"nutrientName":"STARCH","product":289,"reference":"EuroFIR1001182 Soft cheese, 60% fidm","referenceId":255,"type":"ProductNutrientAssociation","unit":"g","validCountries":[]},{"amount":0.2,"comment":null,"derived":false,"id":9405,"nutrientId":25,"nutrientName":"SUGAR","product":289,"reference":"EuroFIR1001182 Soft cheese, 60% fidm","referenceId":255,"type":"ProductNutrientAssociation","unit":"g","validCountries":[]},{"amount":0.2,"comment":null,"derived":false,"id":9406,"nutrientId":26,"nutrientName":"THIA","product":289,"reference":"EuroFIR1001182 Soft cheese, 60% fidm","referenceId":255,"type":"ProductNutrientAssociation","unit":"mg","validCountries":[]},{"amount":0.2,"comment":null,"derived":false,"id":9407,"nutrientId":27,"nutrientName":"VITB12","product":289,"reference":"EuroFIR1001182 Soft cheese, 60% fidm","referenceId":255,"type":"ProductNutrientAssociation","unit":"ug","validCountries":[]},{"amount":0.2,"comment":null,"derived":false,"id":9408,"nutrientId":28,"nutrientName":"VITB6","product":289,"reference":"EuroFIR1001182 Soft cheese, 60% fidm","referenceId":255,"type":"ProductNutrientAssociation","unit":"mg","validCountries":[]},{"amount":0.2,"comment":null,"derived":false,"id":9409,"nutrientId":29,"nutrientName":"VITC","product":289,"reference":"EuroFIR1001182 Soft cheese, 60% fidm","referenceId":255,"type":"ProductNutrientAssociation","unit":"mg","validCountries":[]},{"amount":0.2,"comment":null,"derived":false,"id":9410,"nutrientId":30,"nutrientName":"VITD","product":289,"reference":"EuroFIR1001182 Soft cheese, 60% fidm","referenceId":255,"type":"ProductNutrientAssociation","unit":"ug","validCountries":[]},{"amount":0.2,"comment":null,"derived":false,"id":9411,"nutrientId":31,"nutrientName":"VITE","product":289,"reference":"EuroFIR1001182 Soft cheese, 60% fidm","referenceId":255,"type":"ProductNutrientAssociation","unit":"ATE","validCountries":[]},{"amount":0.2,"comment":null,"derived":false,"id":9412,"nutrientId":32,"nutrientName":"WATER","product":289,"reference":"EuroFIR1001182 Soft cheese, 60% fidm","referenceId":255,"type":"ProductNutrientAssociation","unit":"g","validCountries":[]},{"amount":0.2,"comment":null,"derived":false,"id":9413,"nutrientId":33,"nutrientName":"ZN","product":289,"reference":"EuroFIR1001182 Soft cheese, 60% fidm","referenceId":255,"type":"ProductNutrientAssociation","unit":"mg","validCountries":[]}],"possibleOrigins":[],"processes":[],"processesCo2":[],"specification":"weich","startOfLocalSeason":"None","synonyms":[],"tags":[],"texture":null,"unitWeights":[]}