{"allergenes":[],"alternatives":[],"co2Values":[{"amount":0.2,"baseValue":10113,"comment":"co2-calculation: wie Steinpilz\r\n calculation-process-documentation: -","derived":true,"id":16149,"product":343,"type":"Co2Value","unit":"kg CO2 Äq/kg","validCountries":[]}],"commentsOnDensityAndUnitWeight":"","densities":[],"edb":true,"endOfLocalSeason":"None","englishName":"chantarelle","foodWasteData":[],"frenchName":null,"id":343,"infoTextForCook":null,"name":"Pfifferlinge","nutrientProcesses":[],"nutrients":[{"amount":0.2,"comment":null,"derived":false,"id":11390,"nutrientId":1,"nutrientName":"ALC","product":343,"reference":"EuroFIR1000839 Chanterelle, raw","referenceId":298,"type":"ProductNutrientAssociation","unit":"g","validCountries":[]},{"amount":0.2,"comment":null,"derived":false,"id":11391,"nutrientId":2,"nutrientName":"CA","product":343,"reference":"EuroFIR1000839 Chanterelle, raw","referenceId":298,"type":"ProductNutrientAssociation","unit":"mg","validCountries":[]},{"amount":0.2,"comment":null,"derived":false,"id":11392,"nutrientId":3,"nutrientName":"CHO","product":343,"reference":"EuroFIR1000839 Chanterelle, raw","referenceId":298,"type":"ProductNutrientAssociation","unit":"g","validCountries":[]},{"amount":0.2,"comment":null,"derived":false,"id":11393,"nutrientId":4,"nutrientName":"CHORL","product":343,"reference":"EuroFIR1000839 Chanterelle, raw","referenceId":298,"type":"ProductNutrientAssociation","unit":"mg","validCountries":[]},{"amount":0.2,"comment":null,"derived":false,"id":11394,"nutrientId":5,"nutrientName":"CHOT","product":343,"reference":"EuroFIR1000839 Chanterelle, raw","referenceId":298,"type":"ProductNutrientAssociation","unit":"g","validCountries":[]},{"amount":0.2,"comment":null,"derived":false,"id":11395,"nutrientId":6,"nutrientName":"CLD","product":343,"reference":"EuroFIR1000839 Chanterelle, raw","referenceId":298,"type":"ProductNutrientAssociation","unit":"mg","validCountries":[]},{"amount":0.2,"comment":null,"derived":false,"id":11396,"nutrientId":7,"nutrientName":"ENERC","product":343,"reference":"EuroFIR1000839 Chanterelle, raw","referenceId":298,"type":"ProductNutrientAssociation","unit":"kJ","validCountries":[]},{"amount":0.2,"comment":null,"derived":false,"id":11397,"nutrientId":8,"nutrientName":"FAMS","product":343,"reference":"EuroFIR1000839 Chanterelle, raw","referenceId":298,"type":"ProductNutrientAssociation","unit":"g","validCountries":[]},{"amount":0.2,"comment":null,"derived":false,"id":11398,"nutrientId":9,"nutrientName":"FAPU","product":343,"reference":"EuroFIR1000839 Chanterelle, raw","referenceId":298,"type":"ProductNutrientAssociation","unit":"g","validCountries":[]},{"amount":0.2,"comment":null,"derived":false,"id":11399,"nutrientId":10,"nutrientName":"FASAT","product":343,"reference":"EuroFIR1000839 Chanterelle, raw","referenceId":298,"type":"ProductNutrientAssociation","unit":"g","validCountries":[]},{"amount":0.2,"comment":null,"derived":false,"id":11400,"nutrientId":11,"nutrientName":"FAT","product":343,"reference":"EuroFIR1000839 Chanterelle, raw","referenceId":298,"type":"ProductNutrientAssociation","unit":"g","validCountries":[]},{"amount":0.2,"comment":null,"derived":false,"id":11401,"nutrientId":12,"nutrientName":"FE","product":343,"reference":"EuroFIR1000839 Chanterelle, raw","referenceId":298,"type":"ProductNutrientAssociation","unit":"mg","validCountries":[]},{"amount":0.2,"comment":null,"derived":false,"id":11402,"nutrientId":13,"nutrientName":"FIBT","product":343,"reference":"EuroFIR1000839 Chanterelle, raw","referenceId":298,"type":"ProductNutrientAssociation","unit":"g","validCountries":[]},{"amount":0.2,"comment":null,"derived":false,"id":11403,"nutrientId":14,"nutrientName":"FOL","product":343,"reference":"EuroFIR1000839 Chanterelle, raw","referenceId":298,"type":"ProductNutrientAssociation","unit":"ug","validCountries":[]},{"amount":0.2,"comment":null,"derived":false,"id":11404,"nutrientId":15,"nutrientName":"ID","product":343,"reference":"EuroFIR1000839 Chanterelle, raw","referenceId":298,"type":"ProductNutrientAssociation","unit":"ug","validCountries":[]},{"amount":0.2,"comment":null,"derived":false,"id":11405,"nutrientId":16,"nutrientName":"K","product":343,"reference":"EuroFIR1000839 Chanterelle, raw","referenceId":298,"type":"ProductNutrientAssociation","unit":"mg","validCountries":[]},{"amount":0.2,"comment":null,"derived":false,"id":11406,"nutrientId":17,"nutrientName":"MG","product":343,"reference":"EuroFIR1000839 Chanterelle, raw","referenceId":298,"type":"ProductNutrientAssociation","unit":"mg","validCountries":[]},{"amount":0.2,"comment":null,"derived":false,"id":11407,"nutrientId":18,"nutrientName":"NA","product":343,"reference":"EuroFIR1000839 Chanterelle, raw","referenceId":298,"type":"ProductNutrientAssociation","unit":"mg","validCountries":[]},{"amount":0.2,"comment":null,"derived":false,"id":11408,"nutrientId":19,"nutrientName":"NIA","product":343,"reference":"EuroFIR1000839 Chanterelle, raw","referenceId":298,"type":"ProductNutrientAssociation","unit":"mg","validCountries":[]},{"amount":0.2,"comment":null,"derived":false,"id":11409,"nutrientId":20,"nutrientName":"P","product":343,"reference":"EuroFIR1000839 Chanterelle, raw","referenceId":298,"type":"ProductNutrientAssociation","unit":"mg","validCountries":[]},{"amount":0.2,"comment":null,"derived":false,"id":11410,"nutrientId":21,"nutrientName":"PANTAC","product":343,"reference":"EuroFIR1000839 Chanterelle, raw","referenceId":298,"type":"ProductNutrientAssociation","unit":"mg","validCountries":[]},{"amount":0.2,"comment":null,"derived":false,"id":11411,"nutrientId":22,"nutrientName":"PROT","product":343,"reference":"EuroFIR1000839 Chanterelle, raw","referenceId":298,"type":"ProductNutrientAssociation","unit":"g","validCountries":[]},{"amount":0.2,"comment":null,"derived":false,"id":11412,"nutrientId":23,"nutrientName":"RIBF","product":343,"reference":"EuroFIR1000839 Chanterelle, raw","referenceId":298,"type":"ProductNutrientAssociation","unit":"mg","validCountries":[]},{"amount":0.2,"comment":null,"derived":false,"id":11413,"nutrientId":24,"nutrientName":"STARCH","product":343,"reference":"EuroFIR1000839 Chanterelle, raw","referenceId":298,"type":"ProductNutrientAssociation","unit":"g","validCountries":[]},{"amount":0.2,"comment":null,"derived":false,"id":11414,"nutrientId":25,"nutrientName":"SUGAR","product":343,"reference":"EuroFIR1000839 Chanterelle, raw","referenceId":298,"type":"ProductNutrientAssociation","unit":"g","validCountries":[]},{"amount":0.2,"comment":null,"derived":false,"id":11415,"nutrientId":26,"nutrientName":"THIA","product":343,"reference":"EuroFIR1000839 Chanterelle, raw","referenceId":298,"type":"ProductNutrientAssociation","unit":"mg","validCountries":[]},{"amount":0.2,"comment":null,"derived":false,"id":11416,"nutrientId":27,"nutrientName":"VITB12","product":343,"reference":"EuroFIR1000839 Chanterelle, raw","referenceId":298,"type":"ProductNutrientAssociation","unit":"ug","validCountries":[]},{"amount":0.2,"comment":null,"derived":false,"id":11417,"nutrientId":28,"nutrientName":"VITB6","product":343,"reference":"EuroFIR1000839 Chanterelle, raw","referenceId":298,"type":"ProductNutrientAssociation","unit":"mg","validCountries":[]},{"amount":0.2,"comment":null,"derived":false,"id":11418,"nutrientId":29,"nutrientName":"VITC","product":343,"reference":"EuroFIR1000839 Chanterelle, raw","referenceId":298,"type":"ProductNutrientAssociation","unit":"mg","validCountries":[]},{"amount":0.2,"comment":null,"derived":false,"id":11419,"nutrientId":30,"nutrientName":"VITD","product":343,"reference":"EuroFIR1000839 Chanterelle, raw","referenceId":298,"type":"ProductNutrientAssociation","unit":"ug","validCountries":[]},{"amount":0.2,"comment":null,"derived":false,"id":11420,"nutrientId":31,"nutrientName":"VITE","product":343,"reference":"EuroFIR1000839 Chanterelle, raw","referenceId":298,"type":"ProductNutrientAssociation","unit":"ATE","validCountries":[]},{"amount":0.2,"comment":null,"derived":false,"id":11421,"nutrientId":32,"nutrientName":"WATER","product":343,"reference":"EuroFIR1000839 Chanterelle, raw","referenceId":298,"type":"ProductNutrientAssociation","unit":"g","validCountries":[]},{"amount":0.2,"comment":null,"derived":false,"id":11422,"nutrientId":33,"nutrientName":"ZN","product":343,"reference":"EuroFIR1000839 Chanterelle, raw","referenceId":298,"type":"ProductNutrientAssociation","unit":"mg","validCountries":[]}],"possibleOrigins":[],"processes":[],"processesCo2":[],"specification":null,"startOfLocalSeason":"None","synonyms":[],"tags":[],"texture":null,"unitWeights":[]}